find_git_repository
djangy
