Metadata-Version: 1.0
Name: Djangy
Version: 0.13
Summary: Djangy.com client application
Home-page: http://www.djangy.com
Author: David J. Paola
Author-email: dave@djangy.com
License: UNKNOWN
Keywords: djangy django
Platform: UNKNOWN
